{
   
               "steps" : [
                  {
                     "distance" : {
                        "text" : "0.3 mi",
                        "value" : 448
                     },
                     "duration" : {
                        "text" : "1 min",
                        "value" : 60
                     },
                     "end_location" : {
                        "lat" : 37.774790,
                        "lng" : -122.4010
                     },
                     "html_instructions" : "Head \u003cb\u003enortheast\u003c/b\u003e on \u003cb\u003eBrannan St\u003c/b\u003e toward \u003cb\u003eLangton St\u003c/b\u003e",
                     "polyline" : {
                        "points" : "uipeFzcbjV}AuBi@u@sAiBk@w@i@s@_AqA[a@IKmAeB_@i@q@aA"
                     },
                     "start_location" : {
                        "lat" : 37.771950,
                        "lng" : -122.404620
                     },
                     "travel_mode" : "DRIVING"
                  },
                  {
                     "distance" : {
                        "text" : "0.6 mi",
                        "value" : 916
                     },
                     "duration" : {
                        "text" : "1 min",
                        "value" : 75
                     },
                     "end_location" : {
                        "lat" : 37.76777000000001,
                        "lng" : -122.396370
                     },
                     "html_instructions" : "Turn \u003cb\u003eright\u003c/b\u003e onto the \u003cb\u003eInterstate 280 S\u003c/b\u003e ramp to \u003cb\u003eSan Jose\u003c/b\u003e",
                     "polyline" : {
                        "points" : "m{peFfmajVf@YhA}@VSPMFGPSRWPWT[\\a@?A@A@An@{@bAwAFIHI@CFIRS`@[@A?ADA^Sh@SPEBARK`@IF?`@EfAC|AEpAENA^Ch@I`@KZIn@Un@Y^Ud@[ZWLMPOJMJKV[T[PUBC@C@CFY"
                     },
                     "start_location" : {
                        "lat" : 37.774790,
                        "lng" : -122.4010
                     },
                     "travel_mode" : "DRIVING"
                  },
                  {
                     "distance" : {
                        "text" : "2.3 mi",
                        "value" : 3749
                     },
                     "duration" : {
                        "text" : "2 mins",
                        "value" : 136
                     },
                     "end_location" : {
                        "lat" : 37.73750,
                        "lng" : -122.402170
                     },
                     "html_instructions" : "Merge onto \u003cb\u003eI-280 S\u003c/b\u003e",
                     "polyline" : {
                        "points" : "qooeFhp`jVbDiE`AwA@?PWDGLONQLQZ[`BuA|@q@VOXORKRKh@UVKzAe@@?`AQbAIxDWvAI`F[hBIXA^An@CbACpACvA?r@?T?pA@J?V?@?`A@r@@`@?p@?`@A`@Ax@IZC`BWt@OVGZKdCo@hASlBWx@G^Cn@AB?Z?z@Bl@Bd@DZFXDh@H\\HTFj@PXJBBPFd@Rf@RHBTHRJJDhA`@D@f@Rv@V|CjA@?nDvAhBt@tAh@LHRJ`Aj@`@Vj@^d@^ZXZVB@`A~@t@r@HHd@`@pAjA`BrAJJj@d@f@d@PNb@\\?@f@`@PPfA|@?@d@`@vAnA@@PN`BvA@@JHhB~ADB?@@?@@b@\\VTDBv@v@B@`@`@bAz@PR@@z@|@t@x@BD?@`AjARX\\b@"
                     },
                     "start_location" : {
                        "lat" : 37.76777000000001,
                        "lng" : -122.396370
                     },
                     "travel_mode" : "DRIVING"
                  },
                  {
                     "distance" : {
                        "text" : "7.4 mi",
                        "value" : 11945
                     },
                     "duration" : {
                        "text" : "7 mins",
                        "value" : 442
                     },
                     "end_location" : {
                        "lat" : 37.63793000000001,
                        "lng" : -122.404870
                     },
                     "html_instructions" : "Take the exit on the \u003cb\u003eleft\u003c/b\u003e onto \u003cb\u003eUS-101 S\u003c/b\u003e toward \u003cb\u003eSan Jose\u003c/b\u003e",
                     "polyline" : {
                        "points" : "krieFptajVHF@@@?HFJH@@@@@??@Xd@Vd@v@rA\\r@FLZd@l@|@Z^n@n@\\Xh@Z\\Th@RZLb@JVFf@J\\BP@N@X?VANAD?@?F?TCTCB?NCXERGVGJEXKDARIrAg@RI`@OJEB?N@b@S~BaAp@Wl@Ut@QbAUfB_@@?l@OhB_@jBe@~@W@?z@SLCFAD?B?B?NBb@Od@OlBi@`Bg@t@Sl@Qh@ObAYVGdBg@hA]ZKx@Wv@WdA[zBq@x@WRGp@Q\\KnBe@r@Mx@O|EaAVGxEu@|Bc@|@SnDeAPIXMb@SNIpAs@NIhHsFLInA}@|Aw@nAi@p@UPGZKXId@KlAU`@En@KjAQVCZEfC_@nBW@A|@K\\E`LwAtC_@dDa@v@MvCa@hAQhC_@ZEnAS~B[`r@oJhWqDhC]`C[hAQpAQbEk@lIkA~Cc@|AUnImAzIuAhCWdBIV?ZA^?T?j@@T@`@@p@D`@D|@JjAR^D|A`@x@VhCx@D@?@@?NF`CbAlAh@|@b@lCvAh@Z`BbAf@Z`BhAbBnAjA`AXRB@dAbAfAbAl@j@fAbArFjFbB|AhEbEzAxArAvAp@t@b@h@fAtAv@hAl@~@PZ@DR\\?@@?Vh@R\\@@@B|D`HhGtKxAxB`AjAnAnAnA`A`BdAbAj@jHxC`DtAdA^dAZ~@Vr@NhANB?~@JH@ZBj@Dt@BbA@pACdACfAGbBI~BKhBKh@ATAvAGTApDMzJ_@xMg@~Qw@nAIn@IbBO~@WhAWjAYrA_@rFoB"
                     },
                     "start_location" : {
                        "lat" : 37.73750,
                        "lng" : -122.402170
                     },
                     "travel_mode" : "DRIVING"
                  },
                  {
                     "distance" : {
                        "text" : "0.2 mi",
                        "value" : 255
                     },
                     "duration" : {
                        "text" : "1 min",
                        "value" : 13
                     },
                     "end_location" : {
                        "lat" : 37.63572000000001,
                        "lng" : -122.40410
                     },
                     "html_instructions" : "Take the exit toward \u003cb\u003eNorth Access Rd\u003c/b\u003e",
                     "polyline" : {
                        "points" : "advdFlebjV|AYPGfBi@|Ae@XG\\Id@Kd@I"
                     },
                     "start_location" : {
                        "lat" : 37.63793000000001,
                        "lng" : -122.404870
                     },
                     "travel_mode" : "DRIVING"
                  },
                  {
                     "distance" : {
                        "text" : "1.1 mi",
                        "value" : 1800
                     },
                     "duration" : {
                        "text" : "1 min",
                        "value" : 86
                     },
                     "end_location" : {
                        "lat" : 37.61990,
                        "lng" : -122.400090
                     },
                     "html_instructions" : "Keep \u003cb\u003eleft\u003c/b\u003e at the fork, follow signs for \u003cb\u003eS F Intl Airport\u003c/b\u003e",
                     "polyline" : {
                        "points" : "gvudFr`bjVXIDA@?PCJAZEnFg@TAb@ELCrC]bAK@?jE_@vAQB?LAB?@?pCSzBOzAKrBOnD]x@InAQj@Kn@Kt@Od@MtC_A~DwAtFwAdG}AfEcAdB[`BY"
                     },
                     "start_location" : {
                        "lat" : 37.63572000000001,
                        "lng" : -122.40410
                     },
                     "travel_mode" : "DRIVING"
                  },
                  {
                     "distance" : {
                        "text" : "0.2 mi",
                        "value" : 354
                     },
                     "duration" : {
                        "text" : "1 min",
                        "value" : 33
                     },
                     "end_location" : {
                        "lat" : 37.616820,
                        "lng" : -122.399070
                     },
                     "html_instructions" : "Follow signs for \u003cb\u003eInternational Terminal/Domestic Terminal\u003c/b\u003e",
                     "polyline" : {
                        "points" : "ksrdFpgajVrFgAtD{@|DgA"
                     },
                     "start_location" : {
                        "lat" : 37.61990,
                        "lng" : -122.400090
                     },
                     "travel_mode" : "DRIVING"
                  },
                  {
                     "distance" : {
                        "text" : "0.5 mi",
                        "value" : 790
                     },
                     "duration" : {
                        "text" : "1 min",
                        "value" : 68
                     },
                     "end_location" : {
                        "lat" : 37.61460,
                        "lng" : -122.392650
                     },
                     "html_instructions" : "Keep \u003cb\u003eleft\u003c/b\u003e at the fork",
                     "polyline" : {
                        "points" : "c`rdFdaajV~Aq@vDmAhBq@fAe@RITQVSPWLSP_@J_@BMDQ@M@GB[@[?M?QAYKmAGq@MwAGm@CSE[AQGi@SyAGg@G[Ou@Q}@CKCKSkA"
                     },
                     "start_location" : {
                        "lat" : 37.616820,
                        "lng" : -122.399070
                     },
                     "travel_mode" : "DRIVING"
                  },
                  {
                     "distance" : {
                        "text" : "0.3 mi",
                        "value" : 445
                     },
                     "duration" : {
                        "text" : "1 min",
                        "value" : 40
                     },
                     "end_location" : {
                        "lat" : 37.61530,
                        "lng" : -122.387740
                     },
                     "html_instructions" : "Continue straight",
                     "polyline" : {
                        "points" : "grqdF`y_jVAEOiA?U[sBB[a@iCIaA@WCUE]?CE]COo@cG?g@?c@@S@WFY"
                     },
                     "start_location" : {
                        "lat" : 37.61460,
                        "lng" : -122.392650
                     },
                     "travel_mode" : "DRIVING"
                  },
                  {
                     "distance" : {
                        "text" : "0.3 mi",
                        "value" : 464
                     },
                     "duration" : {
                        "text" : "1 min",
                        "value" : 47
                     },
                     "end_location" : {
                        "lat" : 37.61660000000001,
                        "lng" : -122.383890
                     },
                     "html_instructions" : "Slight \u003cb\u003eright\u003c/b\u003e",
                     "polyline" : {
                        "points" : "svqdFjz~iVh@gBR_APi@DODODSDW?CBS?O?W?A?a@AIAUEQE[K_@CMKUCGIMEIMOQQEG]UGGaAm@OIi@]k@]OIICECIAK?E@"
                     },
                     "start_location" : {
                        "lat" : 37.61530,
                        "lng" : -122.387740
                     },
                     "travel_mode" : "DRIVING"
                  }
               ]
}